.gitignore
LICENSE
MANIFEST.in
README.md
requirements.txt
setup.py
dataspree/platform_sdk/__init__.py
dataspree/platform_sdk/base_model.py
dataspree/platform_sdk/cli.py
dataspree/platform_sdk/client.py
dataspree/platform_sdk/data_loader.py
dataspree/platform_sdk/http_token_authentication.py
dataspree/platform_sdk/query.py
dataspree/platform_sdk/video_upload.py
dataspree/platform_sdk/worker.py
dataspree/platform_sdk/decoder/__init__.py
dataspree/platform_sdk/decoder/base_decoder.py
dataspree/platform_sdk/decoder/opencv_decoder.py
dataspree/platform_sdk/decoder/pcd_decoder.py
dataspree/platform_sdk/decoder/serializer.py
dataspree_platform_sdk.egg-info/PKG-INFO
dataspree_platform_sdk.egg-info/SOURCES.txt
dataspree_platform_sdk.egg-info/dependency_links.txt
dataspree_platform_sdk.egg-info/entry_points.txt
dataspree_platform_sdk.egg-info/requires.txt
dataspree_platform_sdk.egg-info/top_level.txt
dlds-aws-scheduler/Dockerfile
dlds-aws-scheduler/README.md
dlds-aws-scheduler/example_config.yml
dlds-aws-scheduler/requirements.txt
dlds-aws-scheduler/dldsaws/__init__.py
dlds-aws-scheduler/dldsaws/aws_task.py
dlds-aws-scheduler/dldsaws/dlds_aws_scheduler.py
dlds-aws-scheduler/scripts/create_aws_task_definition.py
example/example.py
example/requirements.txt
tests/test_upload.py