Metadata-Version: 2.1
Name: dataspree-platform-sdk
Version: 1.9.8
Summary: Python SDK Data Spree AI Platform
Home-page: https://data-spree.com/ai
Author: Data Spree GmbH
Author-email: info@data-spree.com
License: Apache-2.0
Classifier: License :: OSI Approved :: Apache Software License
Classifier: Programming Language :: Python
Classifier: Programming Language :: Python :: 3
Requires-Python: >=3.6
License-File: LICENSE
Requires-Dist: click~=8.0
Requires-Dist: joblib~=1.1
Requires-Dist: msgpack~=1.0
Requires-Dist: requests~=2.25
Requires-Dist: tqdm~=4.50
Provides-Extra: kitti
Requires-Dist: Pillow<10.0,>=8.0; extra == "kitti"
Provides-Extra: worker
Requires-Dist: aiofiles~=0.8.0; extra == "worker"
Requires-Dist: aiohttp_cors~=0.7; extra == "worker"
Requires-Dist: aiohttp~=3.7; extra == "worker"
Requires-Dist: Pillow<10.0,>=8.0; extra == "worker"
Provides-Extra: build
Requires-Dist: pytest~=7.0; extra == "build"
